functionalstream/__init__.py
functionalstream/decorators.py
functionalstream/functions.py
functionalstream/monad.py
functionalstream/os.py
functionalstream/pipeline.py
functionalstream/stream.py
functionalstream/typing.py
functionalstream-0.1.8.dist-info/LICENSE
functionalstream-0.1.8.dist-info/METADATA
functionalstream-0.1.8.dist-info/WHEEL
functionalstream-0.1.8.dist-info/top_level.txt
functionalstream-0.1.8.dist-info/RECORD
