Metadata-Version: 2.1
Name: functionalstream
Version: 0.1.8
Summary: A functional interface for python iterator
Home-page: https://github.com/cjwcommuny/functionalstream
Author: cjwcommuny
Author-email: cjwcommuny@outlook.com
License: UNKNOWN
Platform: UNKNOWN
Classifier: Programming Language :: Python :: 3
Classifier: License :: OSI Approved :: MIT License
Classifier: Operating System :: OS Independent
Requires-Python: >=3.6
